db_connector_lib/__init__.py
db_connector_lib/mongodb_connector.py
db_connector_lib/mysql_connector.py
db_connector_lib-0.1.0.dist-info/METADATA
db_connector_lib-0.1.0.dist-info/WHEEL
db_connector_lib-0.1.0.dist-info/top_level.txt
db_connector_lib-0.1.0.dist-info/RECORD
