Metadata-Version: 2.4
Name: db-connector-lib
Version: 0.1.0
Summary: A simple DB connector for multiple databases
Author: Preeti Latta
Author-email: preetilatta164@gmail.com
Requires-Python: >=3.7
Requires-Dist: mysql-connector-python
Requires-Dist: pymongo
Dynamic: author
Dynamic: author-email
Dynamic: requires-dist
Dynamic: requires-python
Dynamic: summary
